resolver_athena_client/__init__.py
resolver_athena_client/client/__init__.py
resolver_athena_client/client/athena_client.py
resolver_athena_client/client/athena_options.py
resolver_athena_client/client/channel.py
resolver_athena_client/client/consts.py
resolver_athena_client/client/correlation.py
resolver_athena_client/client/deployment_selector.py
resolver_athena_client/client/exceptions.py
resolver_athena_client/client/image_format_detector.py
resolver_athena_client/client/models/__init__.py
resolver_athena_client/client/models/input_model.py
resolver_athena_client/client/transformers/__init__.py
resolver_athena_client/client/transformers/core.py
resolver_athena_client/client/transformers/worker_batcher.py
resolver_athena_client/client/utils.py
resolver_athena_client/generated/__init__.py
resolver_athena_client/generated/athena/__init__.py
resolver_athena_client/generated/athena/athena_pb2.py
resolver_athena_client/generated/athena/athena_pb2.pyi
resolver_athena_client/generated/athena/athena_pb2_grpc.py
resolver_athena_client/generated/athena/models_pb2.py
resolver_athena_client/generated/athena/models_pb2.pyi
resolver_athena_client/generated/athena/models_pb2_grpc.py
resolver_athena_client/grpc_wrappers/__init__.py
resolver_athena_client/grpc_wrappers/classifier_service.py
resolver_athena_client/py.typed
resolver_athena_client/version.py
resolver_athena_client-1.0.0.dist-info/WHEEL
resolver_athena_client-1.0.0.dist-info/METADATA
resolver_athena_client-1.0.0.dist-info/RECORD
