Metadata-Version: 2.3
Name: resolver-athena-client
Version: 1.0.0
Summary: Python client library for Athena API - CSAM detection and content classification
Keywords: csam,content-detection,image-classification,api-client,grpc
Author: Crisp Thinking Group Ltd
Author-email: Crisp Thinking Group Ltd <opensource@kroll.com>
License: MIT
Classifier: Development Status :: 4 - Beta
Classifier: Intended Audience :: Developers
Classifier: License :: OSI Approved :: MIT License
Classifier: Programming Language :: Python :: 3.10
Classifier: Programming Language :: Python :: 3.11
Classifier: Programming Language :: Python :: 3.12
Classifier: Programming Language :: Python :: 3.13
Requires-Dist: anyio>=4.10.0
Requires-Dist: brotli>=1.1.0
Requires-Dist: grpcio-tools>=1.74.0
Requires-Dist: httpx>=0.25.0
Requires-Dist: numpy>=2.2.6
Requires-Dist: pillow>=11.3.0
Requires-Python: >=3.10
